sanic_babel/__init__.py
sanic_babel/speaklater.py
sanic_babel-0.3.0.dist-info/METADATA
sanic_babel-0.3.0.dist-info/WHEEL
sanic_babel-0.3.0.dist-info/top_level.txt
sanic_babel-0.3.0.dist-info/RECORD
